fastfeedforward/__init__.py
fastfeedforward/fff.py
fastfeedforward/optim/__init__.py
fastfeedforward/optim/local_adam.py
fastfeedforward/optim/local_sgd.py
fastfeedforward-0.2.1.dist-info/LICENSE
fastfeedforward-0.2.1.dist-info/METADATA
fastfeedforward-0.2.1.dist-info/WHEEL
fastfeedforward-0.2.1.dist-info/top_level.txt
fastfeedforward-0.2.1.dist-info/RECORD
