Metadata-Version: 2.1
Name: fastfeedforward
Version: 0.2.1
Summary: A library for the implementation of `O(log(w))` feedforward networks, following the paper "Fast Feedforward Networks"
Home-page: https://github.com/pbelcak/fastfeedforward
Author: Peter Belcak
Author-email: belcak@ethz.ch
Classifier: Programming Language :: Python :: 3
Classifier: Operating System :: OS Independent
Classifier: Topic :: Scientific/Engineering :: Artificial Intelligence
Requires-Python: >=3.9
License-File: LICENSE
Requires-Dist: torch >=1.8.0
